napari_lattice/circle-regular.svg
napari_lattice/disableable.py
napari_lattice/dock_widget.py
napari_lattice/fields.py
napari_lattice/green.png
napari_lattice/grey.png
napari_lattice/icons.py
napari_lattice/invalid.svg
napari_lattice/napari.yaml
napari_lattice/parent_connect.py
napari_lattice/reader.py
napari_lattice/red.png
napari_lattice/shape_selection.py
napari_lattice/shape_selector.py
napari_lattice/utils.py
napari_lattice/valid.svg
napari_lattice-1.0.6.dist-info/METADATA
napari_lattice-1.0.6.dist-info/WHEEL
napari_lattice-1.0.6.dist-info/entry_points.txt
napari_lattice-1.0.6.dist-info/top_level.txt
napari_lattice-1.0.6.dist-info/RECORD
